rheoscale/__init__.py
rheoscale/averages.py
rheoscale/cli.py
rheoscale/config.py
rheoscale/convert_data.py
rheoscale/data_structures.py
rheoscale/errors.py
rheoscale/io.py
rheoscale/plotting_histograms.py
rheoscale/rheoscale_runner.py
rheoscale/schemas.py
rheoscale-0.1.0.dist-info/licenses/LICENSE
rheoscale-0.1.0.dist-info/METADATA
rheoscale-0.1.0.dist-info/WHEEL
rheoscale-0.1.0.dist-info/entry_points.txt
rheoscale-0.1.0.dist-info/top_level.txt
rheoscale-0.1.0.dist-info/RECORD
