Metadata-Version: 2.4
Name: rheoscale
Version: 0.1.0
Summary: RheoScale implementation for DMS analysis
Author: Carter Gray, Liskin Swint-Kruse
Requires-Python: >=3.9
License-File: LICENSE
Requires-Dist: numpy
Requires-Dist: pandas
Dynamic: license-file
